<?xml version="1.0" encoding="utf-8"?>
<LanguageData>

<Miho_Faction_Megacorp.label>Империя Мегакорпорации Михо</Miho_Faction_Megacorp.label>
<Miho_Faction_Megacorp.description>Забытая империя гигантской компании лисьих сомнительных дел где-то в галактике. Причина, по которой они экономят деньги, состоит в том, чтобы сделать жертвоприношение существу, даровавшему им разум.</Miho_Faction_Megacorp.description>
<Miho_Faction_Megacorp.leaderTitle>барон</Miho_Faction_Megacorp.leaderTitle>
<Miho_Faction_Megacorp.pawnSingular>Михо</Miho_Faction_Megacorp.pawnSingular>
<Miho_Faction_Megacorp.pawnsPlural>Михо</Miho_Faction_Megacorp.pawnsPlural>

</LanguageData>

