<?xml version="1.0" encoding="utf-8"?>
<LanguageData>

	<Miho_MeattoDust.label>Извлечение механитовых кристаллов</Miho_MeattoDust.label>
	<Miho_MeattoDust.description>Используйте высокотехнологичное оборудование для извлечения механитовых кристаллов из мяса.</Miho_MeattoDust.description>
	<Miho_MeattoDust.jobString>Извлечение кристаллов.</Miho_MeattoDust.jobString>

	<Miho_StoneChunktoPaste.label>Изготовление керамического теста</Miho_StoneChunktoPaste.label>
	<Miho_StoneChunktoPaste.description>Изготовление керамического теста из каменных глыб.</Miho_StoneChunktoPaste.description>
	<Miho_StoneChunktoPaste.jobString>Изготовление керамического теста.</Miho_StoneChunktoPaste.jobString>

	<Miho_PastetoCeramic.label>Изготовление керамики Михо</Miho_PastetoCeramic.label>
	<Miho_PastetoCeramic.description>Изготовление керамики Михо.</Miho_PastetoCeramic.description>
	<Miho_PastetoCeramic.jobString>Изготовление керамики Михо.</Miho_PastetoCeramic.jobString>

	<Miho_TeatoTea.label>Приготовление Солнечного чая</Miho_TeatoTea.label>
	<Miho_TeatoTea.description>Приготовление чая.</Miho_TeatoTea.description>
	<Miho_TeatoTea.jobString>Приготовление чая.</Miho_TeatoTea.jobString>

	<Miho_SmoketoSmoke.label>Изготовление Солнечных трубок</Miho_SmoketoSmoke.label>
	<Miho_SmoketoSmoke.description>Изготовление Солнечных трубок.</Miho_SmoketoSmoke.description>
	<Miho_SmoketoSmoke.jobString>Изготовление Солнечных трубок.</Miho_SmoketoSmoke.jobString>

	<Miho_ComponentIndustrial.label>Техноткачество</Miho_ComponentIndustrial.label>
	<Miho_ComponentIndustrial.description>Используйте способность Михо ткать технологии и создавать компоненты.</Miho_ComponentIndustrial.description>
	<Miho_ComponentIndustrial.jobString>Ткачество компонента.</Miho_ComponentIndustrial.jobString>

	<Miho_ComponentSpacer.label>Продвинутое техноткачество</Miho_ComponentSpacer.label>
	<Miho_ComponentSpacer.description>Используйте способность Михо ткать технологии и создавать продвинутые компоненты.</Miho_ComponentSpacer.description>
	<Miho_ComponentSpacer.jobString>Ткачество продвинутого компонента.</Miho_ComponentSpacer.jobString>

	<Miho_CookInari.label>Приготовление суши Михо Юбу</Miho_CookInari.label>
	<Miho_CookInari.description>Приготовление суши Михо Юбу с заменителем юбу (хелианто, кукуруза, рис).</Miho_CookInari.description>
	<Miho_CookInari.jobString>Приготовление суши Михо Юбу.</Miho_CookInari.jobString>

	<Miho_CookInarimore.label>Приготовление суши Михо Юбу x4</Miho_CookInarimore.label>
	<Miho_CookInarimore.description>Приготовление суши Михо Юбу с заменителем юбу (хелианто, кукуруза, рис).</Miho_CookInarimore.description>
	<Miho_CookInarimore.jobString>Приготовление суши Михо Юбу.</Miho_CookInarimore.jobString>

	<Miho_JellytoSilk.label>Изготовление Эбоншёлка</Miho_JellytoSilk.label>
	<Miho_JellytoSilk.description>Изготовление Эбоншёлка.</Miho_JellytoSilk.description>
	<Miho_JellytoSilk.jobString>Изготовление Эбоншёлка.</Miho_JellytoSilk.jobString>

</LanguageData>